AUTHORS.rst
CONTRIBUTING.rst
HISTORY.rst
LICENSE
MANIFEST.in
README.rst
setup.cfg
setup.py
gcloudtasks/__init__.py
gcloudtasks/admin.py
gcloudtasks/apps.py
gcloudtasks/executor.py
gcloudtasks/models.py
gcloudtasks/queryset.py
gcloudtasks/queues.py
gcloudtasks/tasks.py
gcloudtasks/urls.py
gcloudtasks/utils.py
gcloudtasks/views.py
gcloudtasks.egg-info/PKG-INFO
gcloudtasks.egg-info/SOURCES.txt
gcloudtasks.egg-info/dependency_links.txt
gcloudtasks.egg-info/not-zip-safe
gcloudtasks.egg-info/requires.txt
gcloudtasks.egg-info/top_level.txt
gcloudtasks/migrations/0001_initial.py
gcloudtasks/migrations/__init__.py
gcloudtasks/static/css/gcloudtasks.css
gcloudtasks/static/js/gcloudtasks.js
gcloudtasks/templates/gcloudtasks/base.html