Metadata-Version: 1.1
Name: gcloudtasks
Version: 0.0.12
Summary: A simplified package to integrate google cloud tasks into your django application within 5 minutes.
Home-page: https://github.com/damey2011/django-gcloud-tasks
Author: Damilola Adeyemi
Author-email: me@dammy.co
License: MIT
Keywords: django-gcloud-tasks
Platform: UNKNOWN
Classifier: Development Status :: 3 - Alpha
Classifier: Framework :: Django :: 2.1
Classifier: Intended Audience :: Developers
Classifier: License :: OSI Approved :: BSD License
Classifier: Natural Language :: English
Classifier: Programming Language :: Python :: 2
Classifier: Programming Language :: Python :: 2.7
Classifier: Programming Language :: Python :: 3
Classifier: Programming Language :: Python :: 3.5
Classifier: Programming Language :: Python :: 3.6
